duoscience/__init__.py
duoscience/client.py
duoscience/utils.py
duoscience_client-0.1.5.dist-info/licenses/LICENSE
duoscience_client-0.1.5.dist-info/METADATA
duoscience_client-0.1.5.dist-info/WHEEL
duoscience_client-0.1.5.dist-info/top_level.txt
duoscience_client-0.1.5.dist-info/RECORD
