Metadata-Version: 2.4
Name: duoscience-client
Version: 0.1.5
Summary: Python client for the DuoScience API.
Home-page: https://github.com/duoscience-ai/duoscience-client
Author: Roman Fitzjalen
Author-email: Roman Fitzjalen <fitzjalen@duoscience.ai>
License: MIT License
Project-URL: Homepage, https://github.com/duoscience-ai/duoscience-client
Project-URL: Bug Tracker, https://github.com/duoscience-ai/duoscience-client/issues
Classifier: Programming Language :: Python :: 3
Classifier: License :: OSI Approved :: MIT License
Classifier: Operating System :: OS Independent
Classifier: Intended Audience :: Developers
Classifier: Topic :: Software Development :: Libraries :: Python Modules
Requires-Python: >=3.9
License-File: LICENSE
Requires-Dist: requests==2.32.3
Requires-Dist: sseclient==0.0.27
Requires-Dist: markdown==3.8.2
Requires-Dist: pdfkit==1.0.0
Requires-Dist: twine==6.1.0
Requires-Dist: wheel==0.45.1
Requires-Dist: setuptools==80.9.0
Requires-Dist: beautifulsoup4==4.13.4
Dynamic: license-file
